MANIFEST.in
README.txt
setup.cfg
setup.py
eximloganalyzer/__init__.py
eximloganalyzer/cli.py
eximloganalyzer/config.py
eximloganalyzer/parser.py
eximloganalyzer/report.py
eximloganalyzer.egg-info/PKG-INFO
eximloganalyzer.egg-info/SOURCES.txt
eximloganalyzer.egg-info/dependency_links.txt
eximloganalyzer.egg-info/entry_points.txt
eximloganalyzer.egg-info/not-zip-safe
eximloganalyzer.egg-info/top_level.txt
tests/badconfig.cfg
tests/exim_mainlog.txt
tests/eximloganalyzer.cfg
tests/tests_configfile.py
tests/tests_configfile.pyc
tests/tests_parser.py
tests/tests_parser.pyc