Metadata-Version: 1.0
Name: eximloganalyzer
Version: 0.1
Summary: Command line script to parse exim logs
Home-page: http://terrarum.net
Author: Joe Topjian
Author-email: joe@terrarum.net
License: BSD
Keywords: exim log analyzer
Platform: UNKNOWN
Classifier: Topic :: Communications :: Email
Classifier: Topic :: Internet :: Log Analysis
